atom_llm/__init__.py
atom_llm/core.py
atom_llm/validator.py
atom_llm-0.1.0.dist-info/METADATA
atom_llm-0.1.0.dist-info/WHEEL
atom_llm-0.1.0.dist-info/RECORD
