Metadata-Version: 2.1
Name: atom-llm
Version: 0.1.0
Summary: 
Author: Zimin(Dennis) Yang
Author-email: Decycle.yang@gmail.com
Requires-Python: >=3.11,<4.0
Classifier: Programming Language :: Python :: 3
Classifier: Programming Language :: Python :: 3.11
Classifier: Programming Language :: Python :: 3.12
Classifier: Programming Language :: Python :: 3.13
Requires-Dist: langchain (>=0.3.13,<0.4.0)
Requires-Dist: langchain-core (==0.3.28)
Requires-Dist: langchain-openai (>=0.2.14,<0.3.0)
Requires-Dist: openai (>=1.58.1,<2.0.0)
